hdf5plugin/__init__.py
hdf5plugin/_config.py
hdf5plugin/_filters.py
hdf5plugin/_utils.py
hdf5plugin/_version.py
hdf5plugin/py.typed
hdf5plugin/test.py
hdf5plugin/plugins/libh5blosc.so
hdf5plugin/plugins/libh5blosc2.so
hdf5plugin/plugins/libh5bshuf.so
hdf5plugin/plugins/libh5bzip2.so
hdf5plugin/plugins/libh5fcidecomp.so
hdf5plugin/plugins/libh5lz4.so
hdf5plugin/plugins/libh5sperr.so
hdf5plugin/plugins/libh5sz.so
hdf5plugin/plugins/libh5sz3.so
hdf5plugin/plugins/libh5zfp.so
hdf5plugin/plugins/libh5zstd.so
hdf5plugin-6.0.0.dist-info/METADATA
hdf5plugin-6.0.0.dist-info/WHEEL
hdf5plugin-6.0.0.dist-info/top_level.txt
hdf5plugin-6.0.0.dist-info/RECORD
hdf5plugin-6.0.0.dist-info/licenses/LICENSE
