Metadata-Version: 2.4
Name: hdf5plugin
Version: 6.0.0
Summary: HDF5 Plugins for Windows, MacOS, and Linux
Author-email: ESRF <silx@esrf.fr>
Project-URL: Homepage, https://github.com/silx-kit/hdf5plugin
Project-URL: Documentation, http://www.silx.org/doc/hdf5plugin/latest/
Project-URL: Repository, https://github.com/silx-kit/hdf5plugin
Classifier: Development Status :: 5 - Production/Stable
Classifier: Environment :: Console
Classifier: Environment :: MacOS X
Classifier: Environment :: Win32 (MS Windows)
Classifier: Intended Audience :: Education
Classifier: Intended Audience :: Science/Research
Classifier: Natural Language :: English
Classifier: Operating System :: POSIX :: Linux
Classifier: Operating System :: MacOS
Classifier: Operating System :: Microsoft :: Windows
Classifier: Programming Language :: Python :: 3
Classifier: Topic :: Software Development :: Libraries :: Python Modules
Requires-Python: >=3.9
License-File: LICENSE
Requires-Dist: h5py>=3.0.0
Provides-Extra: doc
Requires-Dist: ipython; extra == "doc"
Requires-Dist: nbsphinx; extra == "doc"
Requires-Dist: sphinx; extra == "doc"
Requires-Dist: sphinx-autodoc-typehints; extra == "doc"
Requires-Dist: sphinx_rtd_theme; extra == "doc"
Provides-Extra: test
Requires-Dist: numpy<2; python_version == "3.9" and extra == "test"
Requires-Dist: blosc2>=2.5.1; extra == "test"
Requires-Dist: blosc2-grok>=0.2.2; extra == "test"
Provides-Extra: dev
Requires-Dist: hdf5plugin[doc,test]; extra == "dev"
Requires-Dist: bandit; extra == "dev"
Requires-Dist: black; extra == "dev"
Requires-Dist: flake8; extra == "dev"
Requires-Dist: isort; extra == "dev"
Dynamic: license-file
